README.rst
setup.py
Flask_YunPian.egg-info/PKG-INFO
Flask_YunPian.egg-info/SOURCES.txt
Flask_YunPian.egg-info/dependency_links.txt
Flask_YunPian.egg-info/requires.txt
Flask_YunPian.egg-info/top_level.txt
flask_yunpian/__init__.py
flask_yunpian/compat.py