Metadata-Version: 1.0
Name: Flask-YunPian
Version: 0.0.1
Summary: Flask extension for YunPian API
Home-page: https://github.com/codeif/Flask-YunPian
Author: codeif
Author-email: me@codeif.com
License: MIT
Platform: UNKNOWN
